LICENSE
MANIFEST.in
README.rst
environment.yml
requirements-dev.txt
requirements.txt
setup.cfg
setup.py
docs/Makefile
docs/conf.py
docs/examples.rst
docs/index.rst
docs/install.rst
docs/make.bat
docs/modules.rst
docs/requirements.txt
docs/spectrum_example.png
docs/synspec.rst
docs/_static/syn43guide.pdf
docs/_static/synspec.css
python/synspec/__init__.py
python/synspec/atmos.py
python/synspec/atomic.py
python/synspec/models.py
python/synspec/synthesis.py
python/synspec/utils.py
python/synspec.egg-info/PKG-INFO
python/synspec.egg-info/SOURCES.txt
python/synspec.egg-info/dependency_links.txt
python/synspec.egg-info/not-zip-safe
python/synspec.egg-info/requires.txt
python/synspec.egg-info/top_level.txt
python/synspec/data/CIA.H2H2.Yi
python/synspec/data/CIA_H2H.dat
python/synspec/data/CIA_H2H2.dat
python/synspec/data/CIA_H2He.dat
python/synspec/data/CIA_HHe.dat
python/synspec/data/Ca1kas_F_zat.sy
python/synspec/data/Ca2kas_F_zat.sy
python/synspec/data/KIkas.tl
python/synspec/data/Mg1kas_F_ccc.sy
python/synspec/data/Mg2kas_F_ccc.sy
python/synspec/data/NaIkas.tl
python/synspec/data/al1.t
python/synspec/data/al2.t
python/synspec/data/al2_20+9lev.dat
python/synspec/data/al3_19+4lev.dat
python/synspec/data/al4hyd.dat
python/synspec/data/al5hyd.dat
python/synspec/data/ar1_71lev-jK.dat
python/synspec/data/ar2_42+12lev.dat
python/synspec/data/ar3_27+17lev.dat
python/synspec/data/ar4_25+11lev.dat
python/synspec/data/b1.t
python/synspec/data/b2.t
python/synspec/data/be1.t
python/synspec/data/be2.t
python/synspec/data/c1.dat
python/synspec/data/c1.t
python/synspec/data/c2.dat
python/synspec/data/c2.t
python/synspec/data/c3_34+12lev.dat
python/synspec/data/c4.dat
python/synspec/data/ca1.t
python/synspec/data/ca2.t
python/synspec/data/f1.t
python/synspec/data/f2.t
python/synspec/data/fe1.dat
python/synspec/data/fe2p_14+11lev.rap
python/synspec/data/fe2va.dat
python/synspec/data/fe3p_22+7lev.rap
python/synspec/data/fe3va.dat
python/synspec/data/fe4p_21+11lev.rap
python/synspec/data/fe4va.dat
python/synspec/data/fe5p_19+11lev.rap
python/synspec/data/fe5va.dat
python/synspec/data/fe6b.rap
python/synspec/data/fe6v.dat
python/synspec/data/fe7.dat
python/synspec/data/fe7.rap
python/synspec/data/h1.dat
